{
  "qc_case_id": "qc_1752050964_7244",
  "timestamp": "2025-07-09T14:19:24.276616",
  "status": "pending",
  "dual_pipeline_result": {
    "pipeline1": {
      "error": "The operation did not complete (write) (_ssl.c:2427)"
    },
    "pipeline2": {
      "error": "The operation did not complete (write) (_ssl.c:2427)"
    },
    "comparison": {
      "match": false,
      "similarity_score": 0.0,
      "final_transcript": "",
      "qc_required": true,
      "reason": "One or both transcripts are empty"
    },
    "optimal_transcript": ""
  },
  "qc_notes": "",
  "final_decision": null,
  "processed_by": null,
  "processed_at": null,
  "audio_cross_validation": null,
  "optimal_transcript": null
}